gapic_google_maps_streetview_publish_v1-1.0.1-nspkg.pth
gapic_google_maps_streetview_publish_v1-1.0.1.dist-info/DESCRIPTION.rst
gapic_google_maps_streetview_publish_v1-1.0.1.dist-info/METADATA
gapic_google_maps_streetview_publish_v1-1.0.1.dist-info/RECORD
gapic_google_maps_streetview_publish_v1-1.0.1.dist-info/WHEEL
gapic_google_maps_streetview_publish_v1-1.0.1.dist-info/metadata.json
gapic_google_maps_streetview_publish_v1-1.0.1.dist-info/namespace_packages.txt
gapic_google_maps_streetview_publish_v1-1.0.1.dist-info/top_level.txt
google/streetview/__init__.py
google/streetview/publish.py
google/streetview/publish_v1/__init__.py
google/streetview/publish_v1/types.py
google/streetview/publish_v1/gapic/__init__.py
google/streetview/publish_v1/gapic/enums.py
google/streetview/publish_v1/gapic/street_view_publish_service_client.py
google/streetview/publish_v1/gapic/street_view_publish_service_client_config.py
google/streetview/publish_v1/gapic/transports/__init__.py
google/streetview/publish_v1/gapic/transports/street_view_publish_service_grpc_transport.py
google/streetview/publish_v1/proto/__init__.py
google/streetview/publish_v1/proto/resources_pb2.py
google/streetview/publish_v1/proto/resources_pb2_grpc.py
google/streetview/publish_v1/proto/rpcmessages_pb2.py
google/streetview/publish_v1/proto/rpcmessages_pb2_grpc.py
google/streetview/publish_v1/proto/streetview_publish_pb2.py
google/streetview/publish_v1/proto/streetview_publish_pb2_grpc.py
