Metadata-Version: 2.0
Name: gapic-google-maps-streetview-publish-v1
Version: 1.0.1
Summary: Street View Publish API API client library
Home-page: https://github.com/google/streetview-publish-client-libraries/tree/master/client_libraries/python_library
Author: Google LLC
Author-email: googleapis-packages@google.com
License: Apache 2.0
Platform: Posix; MacOS X; Windows
Classifier: Intended Audience :: Developers
Classifier: Development Status :: 3 - Alpha
Classifier: License :: OSI Approved :: Apache Software License
Classifier: Programming Language :: Python
Classifier: Programming Language :: Python :: 2
Classifier: Programming Language :: Python :: 2.7
Classifier: Programming Language :: Python :: 3
Classifier: Programming Language :: Python :: 3.4
Classifier: Programming Language :: Python :: 3.5
Classifier: Programming Language :: Python :: 3.6
Classifier: Operating System :: OS Independent
Classifier: Topic :: Internet
Requires-Dist: google-api-core[grpc] (<2.0.0dev,>=1.4.1)
Requires-Dist: enum34; python_version < "3.4"
